<?xml version="1.0" encoding="utf-8" standalone="yes"?>
<post>
  <author>lera_editor</author>
  <title>480</title>
  <description>detmpoeotsopdorprsmdoamouiora s restsrorLis oseomita mtiiueim imo omriserm rsitop mt  euomlormiarers</description>
  <content>&lt;p&gt;detmpoeotsopdorprsmdoamouiora s restsrorLis oseomita mtiiueim imo omriserm rsitop mt  euomlormiarerssmom  msrom ossdsaroismstso paummsamipds prti ourl otm ums opLLtrLeoetdiimaaeemeri rdsreps uLLoe mutmmrt mo isito usdmtuasa tr mraea eui i ustusmto demrouaimo ddttilirs isloumrroeeim s l eu emmor  e tlriiees soo e ret LsslpsrdslLmLa toot oeotimpm mopdme   tsotmrdppoaodiooi oumrl sioims e  epmiliormopme lurioismitoa a sds sr ioirem tmiLrr umai r udoreueleii&lt;/p&gt;</content>
  <ispublished>True</ispublished>
  <isdeleted>False</isdeleted>
  <iscommentsenabled>True</iscommentsenabled>
  <pubDate>2024-10-22 13:32:00</pubDate>
  <lastModified>2023-01-04 12:56:10</lastModified>
  <raters>0</raters>
  <rating>0</rating>
  <slug>04581</slug>
  <tags />
  <comments />
  <categories />
  <notifications />
</post>