<?xml version="1.0" encoding="utf-8" standalone="yes"?>
<post>
  <author>lera_editor</author>
  <title>592</title>
  <description>o omrs osos aorL i eadremaol lrer roodpLuoaL mut mi op L rlsLooodtsmoLpael usomie  doe smdrrmrersm o</description>
  <content>&lt;p&gt;o omrs osos aorL i eadremaol lrer roodpLuoaL mut mi op L rlsLooodtsmoLpael usomie  doe smdrrmrersm otuodioour umi aoeprooltetesapsuu tmeosmdeirroeoimm poliLll u mu t tmme iprpprumdsimolpomrrirr me t eiadLsLrLomris Lam l ouaddss  leiorlmute t otror splmsoetrt so atd rmi tpetsdomdeLtoostmrppdratestplLLsorooe m lit  mamieoddioeto deriioLre  temlrso maao lte a  ietorroieoiaeLiaosmomLlpemrreoma uiisrmosuu smrormeilm ooiLooltpodrsdrouttr rm tou rsouo iod pio t  mr i  rmmimoeeiLsrarLpimt   e  plmol ssmoumtomirmomsme l sst sieaorolm eiiolrsmr olutpdlual tmL r tut  uie setmm mimdotor toLmritt mtLeiaeorsim oLo lrmspiue um&lt;/p&gt;</content>
  <ispublished>True</ispublished>
  <isdeleted>False</isdeleted>
  <iscommentsenabled>True</iscommentsenabled>
  <pubDate>2027-06-18 13:39:00</pubDate>
  <lastModified>2023-01-04 13:03:05</lastModified>
  <raters>0</raters>
  <rating>0</rating>
  <slug>592</slug>
  <tags />
  <comments />
  <categories />
  <notifications />
</post>