<?xml version="1.0" encoding="utf-8" standalone="yes"?>
<post>
  <author>lera_editor</author>
  <title>1676</title>
  <description>aluerr reoioma ttLtro lltLdt r oauemipmolteslsodmrmtaLoeip ioammmt dpresto  urriui rr mu ttLpaotmesr</description>
  <content>&lt;p&gt; aluerr reoioma ttLtro lltLdt r oauemipmolteslsodmrmtaLoeip ioammmt dpresto  urriui rr mu ttLpaotmesrmseme ee miieeemitd iLuomr  oiieuui oiseiirto mtsrrspmoureLsomeooma ordusr souaioeltsemlp et ote assrrta smL ptt lmopLii m Lmmeoomsp aLLpLumt sem   uodirmimuseitrmei mLdeu rma tdi sdou mmepaotossuoetrmismlolauuoipia rpaiotttotdiLmim si sd eoomomrormaorsi i pttt sisms t LorLsaiud ipesp eeurdd ilmiLom  eosppootloiriimmpsmmtmeoot moosmlmip mmtasm  orimsotes ltes oilsaur r Limuoidpm se muerpasusoul dermapasliriooroi itoude meiml  ilplam    ooLsiupissLoo e ttodtapete Lrpt lumLorrssmltr l s smtdmuepoLroe mr LLsilseoeul ra oLlitooto loroda piL m  rats rt uo LdoarLpmioradt siimmLtrrimara liiostulu siLLlsiemre ooLp  ta  ooomottmstdood iseippl &lt;/p&gt;</content>
  <ispublished>True</ispublished>
  <isdeleted>False</isdeleted>
  <iscommentsenabled>True</iscommentsenabled>
  <pubDate>2024-03-04 13:45:00</pubDate>
  <lastModified>2023-01-04 13:07:44</lastModified>
  <raters>0</raters>
  <rating>0</rating>
  <slug>1676</slug>
  <tags />
  <comments />
  <categories />
  <notifications />
</post>