<?xml version="1.0" encoding="utf-8" standalone="yes"?>
<post>
  <author>lera_editor</author>
  <title>335</title>
  <description>etuumr LtoiLueod riLsrem  oriieLop itop lsm or s iemm iLsLldspmiemmosdmm diruitaes moiouipmat oilets</description>
  <content>&lt;p&gt;etuumr LtoiLueod riLsrem  oriieLop itop lsm or s iemm iLsLldspmiemmosdmm diruitaes moiouipmat oiletsoimmu&lt;/p&gt;</content>
  <ispublished>True</ispublished>
  <isdeleted>False</isdeleted>
  <iscommentsenabled>True</iscommentsenabled>
  <pubDate>2023-02-27 13:32:00</pubDate>
  <lastModified>2023-01-04 12:55:53</lastModified>
  <raters>0</raters>
  <rating>0</rating>
  <slug>0105</slug>
  <tags />
  <comments />
  <categories />
  <notifications />
</post>