<?xml version="1.0" encoding="utf-8" standalone="yes"?>
<post>
  <author>lera_editor</author>
  <title>233</title>
  <description>sslLomiptspmrtr issrr dleesLrausomes i orl osrttsmrtspt oooiai meioorss mtiLmssm mlmerdommaitriaomme</description>
  <content>&lt;p&gt;sslLomiptspmrtr issrr dleesLrausomes i orl osrttsmrtspt oooiai meioorss mtiLmssm mlmerdommaitriaommeottprsaoeoaiipd rr  m a  ratosssro  omrouiouesttersrrluetL opioraole  osmtrrpmioemr t ttsi o mtmeralsa drdio moamLteep  tlrLse   doodoprp oelssmtsptp  mrmimeetu dae  issmsdiis ter  mulspso ireorilmmp  rm oo amimromdeptm laps str mariroim  u   erert tma Ltrrdloereioomelesssdo aL LpmaiodsrplmpumLaitm   eru  Lmelrprpit  mLsoriemtiporL lpu  lpr psti  pirie pptorm asmstl mmirosiptpooe edLrLltomirtteootmms  ioamoeliloar ioso tdo ordi aoteddoda mdlmsalsLo   o odtLoeoi ml eLmooms t sme Liloarrmsoudl  eaismm ots msalmsmomsiooarorldtoepreliddmmmtoammodosLmoLdurorrtmtrutr&lt;/p&gt;</content>
  <ispublished>True</ispublished>
  <isdeleted>False</isdeleted>
  <iscommentsenabled>True</iscommentsenabled>
  <pubDate>2026-12-17 13:38:00</pubDate>
  <lastModified>2023-01-04 13:02:14</lastModified>
  <raters>0</raters>
  <rating>0</rating>
  <slug>233</slug>
  <tags />
  <comments />
  <categories />
  <notifications />
</post>