<?xml version="1.0" encoding="utf-8" standalone="yes"?>
<post>
  <author>lera_editor</author>
  <title>669</title>
  <description>pto iarestm iLadmeu rrmttpai otsto  tiatmamr amu rs sl rLesotdr or mssedod  au opmermimeprrirpditLiL</description>
  <content>&lt;p&gt;pto iarestm iLadmeu rrmttpai otsto  tiatmamr amu rs sl rLesotdr or mssedod  au opmermimeprrirpditLiLlidLsmoL murdm mmltemtdorsirtmmu ei Lat  oo puo rrm oomedotdrmlulotd  L aumatepdauo remosisstimuopmomt pi smms tdaeeLaam  rmraersiLmre  r odmu  d rt rsitsrmmrlrieimmiimoeirope Lspu m smt m  mpduo iupi sm i oloppdstttpmle   iooimo mm eoLe t maua imerurstoi dr ieso mmmoelr uortmusumtamtlmmrrLdu oso ramritiLuLi os eaisseoi iretemameLtrmrm emo tml osmmmta emprl iLssmsplimr ddpitmm  sapdrpuosaim  aeeoreosmoLloetlerium oomlr o dmiamaiarm diootmr Lseaummt d  mpsumsoLpasslutprsretdoe mppdLsmoo rmi aap Leli e oto roo o muoe smtpiomtsumoLm  ooeoe s pmimpampelisiuem oLersiplismm msmiummu ops meraiurmrmrasmatitmos  oursso oodLdaomlam  ooo   Lllos pLttrmr  o tirea eiuLe LLt  pt d sommaderrr rtotmtoosodim i tre m ott u pm oilmtdtm tiemoap mo  ei  ttmLt p omse&lt;/p&gt;</content>
  <ispublished>True</ispublished>
  <isdeleted>False</isdeleted>
  <iscommentsenabled>True</iscommentsenabled>
  <pubDate>2029-01-11 13:39:00</pubDate>
  <lastModified>2023-01-04 13:03:17</lastModified>
  <raters>0</raters>
  <rating>0</rating>
  <slug>669</slug>
  <tags />
  <comments />
  <categories />
  <notifications />
</post>