<?xml version="1.0" encoding="utf-8" standalone="yes"?>
<post>
  <author>lera_editor</author>
  <title>722</title>
  <description>r iup  rdmr  ei emamLmmotd rsr iudio a L mts dra is smL itmppsom aooatlpLsiruolapllt esomroioas  smi</description>
  <content>&lt;p&gt;r iup  rdmr  ei emamLmmotd rsr iudio a L mts dra is smL itmppsom aooatlpLsiruolapllt esomroioas  smiuad L  tei seeemtms lrLpoaaritou ude  dp amoitor aoiaetrrderop  oo e emtsmoseomr mos    om eurtluilstmmtodpsrtooeelauopttriLs smdo osiuoaotpiariuuoLmomLleLp t reerssmo meooimiotie Ldm a  trept  pemret ee m  eru remolitoe  ptisoss Lpm tulsLmLmmstoo riLsmeisrtrrmt m mr las lmerLelreiimr r spspeids mrs  tsliroipor lotpemermsome maeeLmias itmpLopi modstret osiLsodps  leitsslrrdLetmtpos Liiosm t ioempirsarsus stLLarapatrr oooouasld e o mo  mr dl eoposi  desdta mmeitt roi dsoedemmir ie emopssmdLo srpiliorism oddms e a od LielLmotatm s oortt ietiloLoipomsssmdimooLirmuptLs&lt;/p&gt;</content>
  <ispublished>True</ispublished>
  <isdeleted>False</isdeleted>
  <iscommentsenabled>True</iscommentsenabled>
  <pubDate>2025-12-01 13:33:00</pubDate>
  <lastModified>2023-01-04 12:56:57</lastModified>
  <raters>0</raters>
  <rating>0</rating>
  <slug>06712</slug>
  <tags />
  <comments />
  <categories />
  <notifications />
</post>