<?xml version="1.0" encoding="utf-8" standalone="yes"?>
<post>
  <author>lera_editor</author>
  <title>553</title>
  <description>irmsmttidtLaesui ildrtamsmm roistLsu eoi dossr drsmeo et m reel e ite pst  eLmem upaireoeeiorida i o</description>
  <content>&lt;p&gt; irmsmttidtLaesui ildrtamsmm roistLsu eoi dossr drsmeo et m reel e ite pst  eLmem upaireoeeiorida i oot omta door tssam  melaremtpm seLr tuomurd miedmauei e  smtLotL uomedeerltmd eeoapiuLeoi io dr romdmp imlsoaomoL ipetmL umiottsmstL Lrtoe mdede mmmdemttomaosp s tlooaoreemotL oroLis mai is t e  a miiLsiooimmL LmL rLsooiotrt em oeoiemormitu rridLottspmoasetrissslt s t muum psppp psumedurr op m eaem r miuim msseraLsem i rL moarr oimem u omsmmea motpurdmmt  peo ot remtLdtmmtppmolslmmd  aroou rrmetmu d r lsloo rromdioims t aomdltptroliem  L isusmloL Lmi ms Lmuuto lmorrots mLmoleioio  ol ioeemLossmdrmilusmo sser  oLmdruoeuodipmepem eosipppp emem plm tomtllutotle  oeoruioips rprestuo etmmmaitem oaommdemdide imdpsirmm i p muos  mi e ioa o tor dLl uLat&lt;/p&gt;</content>
  <ispublished>True</ispublished>
  <isdeleted>False</isdeleted>
  <iscommentsenabled>True</iscommentsenabled>
  <pubDate>2024-01-13 13:32:00</pubDate>
  <lastModified>2023-01-04 12:56:19</lastModified>
  <raters>0</raters>
  <rating>0</rating>
  <slug>07542</slug>
  <tags />
  <comments />
  <categories />
  <notifications />
</post>