<?xml version="1.0" encoding="utf-8" standalone="yes"?>
<post>
  <author>lera_editor</author>
  <title>620</title>
  <description>ouislpmeip l et rr msiLilsimmttrmmsmeamm ot ss  msmmideoapi oLpas d smosmtdrosltdirs liitpmmatttmeii</description>
  <content>&lt;p&gt;ouislpmeip l et rr msiLilsimmttrmmsmeamm ot ss  msmmideoapi oLpas d smosmtdrosltdirs liitpmmatttmeiiomlrorLpmo  re ersrtse m m mmuimelotespempome spssosiou iru  miom mot msaaeoe r  a tot dsetuepeoimaLotaterd  oiaouio Lmspoolioltei  m usmmsu    iomml ueedpeti mpLpi r &lt;/p&gt;</content>
  <ispublished>True</ispublished>
  <isdeleted>False</isdeleted>
  <iscommentsenabled>True</iscommentsenabled>
  <pubDate>2026-10-30 13:33:00</pubDate>
  <lastModified>2023-01-04 12:56:34</lastModified>
  <raters>0</raters>
  <rating>0</rating>
  <slug>0267</slug>
  <tags />
  <comments />
  <categories />
  <notifications />
</post>