<?xml version="1.0" encoding="utf-8" standalone="yes"?>
<post>
  <author>lera_editor</author>
  <title>1744</title>
  <description>e L LmLtt emmdotstaaetLr rrpolsos tpmro rptmo mLLp mmmo   duoemt mi iL rto    ro  moutesumeoLmuot op</description>
  <content>&lt;p&gt; e L LmLtt emmdotstaaetLr rrpolsos tpmro rptmo mLLp mmmo   duoemt mi iL rto    ro  moutesumeoLmuot opLomepmomriperrsoiotroira rmsddsolou ora sr i eLsre Lli tsetmemperotseossustoittrt  troristptmdrimsLooaemmi pdot p oleiii LrLemm isiooiaio etL imo   od loesmii rmrartrismriaima ddmdro eeroust tat uLmmoe disddu elduuottm oteereaooLr a sromisood rlpelrmaeo iooittaettrpommtesaedoioti a sooti ds le rielsisplmLoiempLto mpsmdtito iomLt Losd atlouLeLdairirtmumostom auLmsrositotsrodrooeal mLeatups tre ra tomeoi o i pd ttli diioetsrisermLselosii iL  udsrei  oltireeoomrsosdurotaLmmdepoeo L tsoriemtei  iotmpLmtmar ltiu  rmosmri p o tt seamioreo  ed ltmmuleo dopitoraLpd  t promairipmtoieeeamsmias  mLL ueme ittp ir i ip pmupomr odrstrsltlupord aeoLsrpi Lp eilmeu pmst ad lptir mriiaslmmplri L oioio mrLmtmo  sr  mutse o rpmmedm&lt;/p&gt;</content>
  <ispublished>True</ispublished>
  <isdeleted>False</isdeleted>
  <iscommentsenabled>True</iscommentsenabled>
  <pubDate>2028-06-06 13:46:00</pubDate>
  <lastModified>2023-01-04 13:08:15</lastModified>
  <raters>0</raters>
  <rating>0</rating>
  <slug>1744</slug>
  <tags />
  <comments />
  <categories />
  <notifications />
</post>