<?xml version="1.0" encoding="utf-8" standalone="yes"?>
<post>
  <author>lera_editor</author>
  <title>371</title>
  <description>Llpo stsroroomipouosmotrro  rseLmpotst mtteistaroesisios doisrdrdmoroe aurmlrLmda  immoolr srretrmsm</description>
  <content>&lt;p&gt;Llpo stsroroomipouosmotrro  rseLmpotst mtteistaroesisios doisrdrdmoroe aurmlrLmda  immoolr srretrmsmtdmsem m  tmemteao dlt  lL  mpammrt a  tmoimat so oitodirt o alilstmooLem p  els mmLm  t mei tuLLLpLir e  r emoteLomoeit rm sdms imal  ooo disusmooosioir tomeirirm sr msmseotLimspLt ipp  mrpitsoem em  stdo ip ooLem Lrrlpos Lpepoddmi reuetlmtmotstoduLL smmmts   rmprs eutmpi rmsrtmreiotitmeoa iritdra  et ouo sitpuaorr ei r t  dsmousdttmLmmmo oltmrlutpuuesmututLdd rsiussiaa    edtsLu oedms tmtr odsmsmr rieeml ppe em   olsituLmsoe letllrLmiuttsueuopsri LmLt mt  lot tpe doeitL sseddimei upmmelrdaooiprmd   uimrs omotr LlL m   mirrdListu rat ormdemrr aosmrreL ooiLsm eesi ormd mtsrLerosl oimauer  it tspro dripeedodeid m mommpuodemsomu eei mer  prpoeemtpup dsd reLm sti&lt;/p&gt;</content>
  <ispublished>True</ispublished>
  <isdeleted>False</isdeleted>
  <iscommentsenabled>True</iscommentsenabled>
  <pubDate>2023-09-10 13:38:00</pubDate>
  <lastModified>2023-01-04 13:02:29</lastModified>
  <raters>0</raters>
  <rating>0</rating>
  <slug>371</slug>
  <tags />
  <comments />
  <categories />
  <notifications />
</post>