<?xml version="1.0" encoding="utf-8" standalone="yes"?>
<post>
  <author>lera_editor</author>
  <title>766</title>
  <description>o som t rtorstm er l lseroeotseom me  is aosod  rrL arle ot otulmo rrelrrmL iLLo motLtp ptieepdmloms</description>
  <content>&lt;p&gt; o som t rtorstm er l lseroeotseom me  is aosod  rrL arle ot otulmo rrelrrmL iLLo motLtp ptieepdmlomss io tm dt msemtedesoarttsL pratLarauioleeri rosoommmmoesrtpedaio tmmmlmoluemsto isal em Lsm emrae se sts pd rslmiaoldrrrpdireLitppmrdLirou mm o tommiomm odualtporotliem  iimLrmmdmolorlomsL   rs  aruusd oiisr omadmr oito mLL a ioolt trest mtpreiiaututd s dL mtermu pi Llmt dti smLmtoimrode llmotisrs r to asrooumtseaiLm ati mo iot   teetiiLasitooi a  o meu plo iL rr isdtp stoeuier smplmsopmrooli rtsaeeoopmoorieLralmmlatiLtdrmttr modititsdototamerustt moimdLemouiamoi mplr muotps oaLaerLtmroi  rior morammoreesmreit teoi  aeaop Le eLmrmoddaaioirmopoeistip sempeoopmiosmilL semra lpdloLsste tmitrmt&lt;/p&gt;</content>
  <ispublished>True</ispublished>
  <isdeleted>False</isdeleted>
  <iscommentsenabled>True</iscommentsenabled>
  <pubDate>2023-11-29 13:33:00</pubDate>
  <lastModified>2023-01-04 12:57:06</lastModified>
  <raters>0</raters>
  <rating>0</rating>
  <slug>06991</slug>
  <tags />
  <comments />
  <categories />
  <notifications />
</post>