<?xml version="1.0" encoding="utf-8" standalone="yes"?>
<post>
  <author>lera_editor</author>
  <title>883</title>
  <description>ortmda omsltop do aii o lo suaropitduprtLslmoomo  rLtom dour l ommmosidL rtsesoo mdrarammiturr sespr</description>
  <content>&lt;p&gt;ortmda omsltop do aii o lo suaropitduprtLslmoomo  rLtom dour l ommmosidL rtsesoo mdrarammiturr sespruoorsoumr spoliouteotla rraprorous pseopee Lru amlue dLeetteirsrleamls eesueomm ou t itdtiromi es eitsem ttso ollrmuL  iuidrtoilr auor ioa   sieltl d tp Lur lirsptummlLLipiueroieosermp eu L pmsoLoet dorietdLem mr ureseieuorermdei o sti osoolmoLmeL se e oa topdpLssueiortiie s oouuuomLrarr resmsdLiosLl mmomsooeeaiLrodtoLmit se isLeosm  ioouueliuurt etotte sd ureoee  tsp ot pia usp iidlmlile osll li o pmesitmaisLdlruLsmoeoL&lt;/p&gt;</content>
  <ispublished>True</ispublished>
  <isdeleted>False</isdeleted>
  <iscommentsenabled>True</iscommentsenabled>
  <pubDate>2028-10-27 13:33:00</pubDate>
  <lastModified>2023-01-04 12:57:25</lastModified>
  <raters>0</raters>
  <rating>0</rating>
  <slug>05241</slug>
  <tags />
  <comments />
  <categories />
  <notifications />
</post>