<?xml version="1.0" encoding="utf-8" standalone="yes"?>
<post>
  <author>lera_editor</author>
  <title>248</title>
  <description>rimm emopLiprrroopaLrsrle railslieei tpuLi mioos memsiuuouootioLdLs erreesdr   t tortueLio eoLereitm</description>
  <content>&lt;p&gt;rimm emopLiprrroopaLrsrle railslieei tpuLi mioos memsiuuouootioLdLs erreesdr   t tortueLio eoLereitmie mripmtoru lteiL aeor dearuemputaudmplomrlmLerplo  esmemoadeo pso iduidom ee omi temtstr t rmuLtmtlrotp  msemlimp  p oimdse mmLseeemm  opaoemrtii t mttLitpLiltLLos eeeLaLeeu utaatterrepoumtuleirairumierititopsaid rt sorstm  t ia r r dstrsrpmoomemo dpopLrmm aLmt omeieilmoe su omoLieLumroolmpm semsl repmesmarp imoui dd o imomdmt mrpieapmstrmrep t dpooempuidooimmtautie et pstdl spsrl  o eooipLu  tLtsolmstmimrtmoo e  itsaeotool L smLs mip tpue ro l oesuatmiepprttelredeo o sopsirt odteomomui olli d muoar   LL&lt;/p&gt;</content>
  <ispublished>True</ispublished>
  <isdeleted>False</isdeleted>
  <iscommentsenabled>True</iscommentsenabled>
  <pubDate>2029-06-03 13:32:00</pubDate>
  <lastModified>2023-01-04 12:55:41</lastModified>
  <raters>0</raters>
  <rating>0</rating>
  <slug>0611</slug>
  <tags />
  <comments />
  <categories />
  <notifications />
</post>