<?xml version="1.0" encoding="utf-8" standalone="yes"?>
<post>
  <author>lera_editor</author>
  <title>244</title>
  <description>dlLoa t Lo eupiisttssmLodl l opeipap rsmimslati L a eple d droiotrmi</description>
  <content>&lt;p&gt;dlLoa t Lo eupiisttssmLodl l opeipap rsmimslati L a eple d droiotrmi&lt;/p&gt;</content>
  <ispublished>True</ispublished>
  <isdeleted>False</isdeleted>
  <iscommentsenabled>True</iscommentsenabled>
  <pubDate>2029-03-14 13:38:00</pubDate>
  <lastModified>2023-01-04 13:02:15</lastModified>
  <raters>0</raters>
  <rating>0</rating>
  <slug>244</slug>
  <tags />
  <comments />
  <categories />
  <notifications />
</post>