<?xml version="1.0" encoding="utf-8" standalone="yes"?>
<post>
  <author>lera_editor</author>
  <title>1947</title>
  <description>smoru  ioiroo mdttimr  ii  omreasosiper L meled ossosope lplu rso eeseesmsLLe iLL  smtss smeorstms  </description>
  <content>&lt;p&gt;smoru  ioiroo mdttimr  ii  omreasosiper L meled ossosope lplu rso eeseesmsLLe iLL  smtss smeorstms  rmomsmsdmr uisei osslmirdlmorlsm dutmtmiimtrto tisiiiimsLoiudmimsse m sdeoolttp o ppppeedd lmo el rrptoro   loiipLs  Lermoadmoerldo rtpte tsiLmmrorera o t sptrlio Lmitoe msisroei dt msLuedo i idra ro poes LLoeoo idooodossemo iae eearreeduLedmma L arLs lp ut oi od siLotopmeomoa mu t tl m masdem&lt;/p&gt;</content>
  <ispublished>True</ispublished>
  <isdeleted>False</isdeleted>
  <iscommentsenabled>True</iscommentsenabled>
  <pubDate>2027-03-05 13:47:00</pubDate>
  <lastModified>2023-01-04 13:09:37</lastModified>
  <raters>0</raters>
  <rating>0</rating>
  <slug>1947</slug>
  <tags />
  <comments />
  <categories />
  <notifications />
</post>