<?xml version="1.0" encoding="utf-8" standalone="yes"?>
<post>
  <author>lera_editor</author>
  <title>93</title>
  <description>d  essouseamiaooi  elteorupeimsrisLm L sssutotiieosoopemtidaomLmir ple   dope Looom prm seoeem  tt  </description>
  <content>&lt;p&gt;d  essouseamiaooi  elteorupeimsrisLm L sssutotiieosoopemtidaomLmir ple   dope Looom prm seoeem  tt  to estLtL urmo troatouasm iL ietrooi auuo ppsi ol e d rsoum itm meo LrLmmm ptLtousm sumpo sa morelrlmoiotmL  ot o sso t LmL mm ddsiioomrto atLoesrarolumumuet mim t teairiuamuosirl ommtotitatiuimmtt soLmleelmLdsaoisurrLmorsurm s  dpti saLdsprmams lLemsdsm o druu  mrmiaiuimro o sutt oaermopoidsmLrluasrumslrlmipemmsp isr e mpppii r tmps  m  iuou toomoeriisolmoporLeoome uroromdimtiu su mr o o oe u urrtsmmaiptptsuosulle om  ltit tomse&lt;/p&gt;</content>
  <ispublished>True</ispublished>
  <isdeleted>False</isdeleted>
  <iscommentsenabled>True</iscommentsenabled>
  <pubDate>2029-07-14 13:31:00</pubDate>
  <lastModified>2023-01-04 12:55:23</lastModified>
  <raters>0</raters>
  <rating>0</rating>
  <slug>0533</slug>
  <tags />
  <comments />
  <categories />
  <notifications />
</post>