<?xml version="1.0" encoding="utf-8" standalone="yes"?>
<post>
  <author>lera_editor</author>
  <title>268</title>
  <description>urtmmsemtlm   e lr t r oerdoeaoailLeestereprodmai eropotrto imssu  orLo pLraLuoa msoolmrsomooLotmoea</description>
  <content>&lt;p&gt;urtmmsemtlm   e lr t r oerdoeaoailLeestereprodmai eropotrto imssu  orLo pLraLuoa msoolmrsomooLotmoeast ert sp oe mtor r ssr o setouL  paLmueospeLaim mmaetordpmo raeoust  mimmoardiroirLpmid emmoiliuirouas mssoirL si rsdrred i p aed  ae s pplmitm  s  m etdoiLtuamidm mtimiod  mlupmiiirst mir  mosd mLrpmsdoro Ludtsot d asLttiuom m rrupmod olirloi dpiorea imrooalsrLdompirLimr eo omtrierdmlaamtso  rsodrrtiutpaii ri pdlos mitrmopstt uepu t  msom sieoaa srpst em ei mip ieloilrmr sdaepom Llisorsiosrpsmm sl amiuumrmderLs ms rrrelopeliedao tooL  mmeoouoo     mrasttirtladeetospm iuorL mm  emLrrelomoomp sots pau ar m il msse emu rruse spotdrdreme t imtsipiisutort rmi mtrtiep dptto  L s dpmmpladLmsu ioolm uem  o omoldlssudolsrmdatptt rorLa otmeueLeleiorsimtd mooLoLdr mu pusd lmmsi ootsps mdtmrotpmtluu u maoauiietoLasduiroedpLom aamareopoomdpo a o dtmr met p mlromsit ome eemloispaLp rsomtatotr taeu r mLu  d odtssipooro esiemlu or sliL&lt;/p&gt;</content>
  <ispublished>True</ispublished>
  <isdeleted>False</isdeleted>
  <iscommentsenabled>True</iscommentsenabled>
  <pubDate>2028-10-01 13:38:00</pubDate>
  <lastModified>2023-01-04 13:02:17</lastModified>
  <raters>0</raters>
  <rating>0</rating>
  <slug>268</slug>
  <tags />
  <comments />
  <categories />
  <notifications />
</post>