<?xml version="1.0" encoding="utf-8" standalone="yes"?>
<post>
  <author>lera_editor</author>
  <title>518</title>
  <description>msomoietord l t orirtu rraLdmmmemtoauddditmd  im meem solLooulri ueirutsros smr losao  ippslsemumu r</description>
  <content>&lt;p&gt;msomoietord l t orirtu rraLdmmmemtoauddditmd  im meem solLooulri ueirutsros smr losao  ippslsemumu r mui ps i smpoemuotadi m  o e &lt;/p&gt;</content>
  <ispublished>True</ispublished>
  <isdeleted>False</isdeleted>
  <iscommentsenabled>True</iscommentsenabled>
  <pubDate>2030-02-26 13:32:00</pubDate>
  <lastModified>2023-01-04 12:56:15</lastModified>
  <raters>0</raters>
  <rating>0</rating>
  <slug>0130</slug>
  <tags />
  <comments />
  <categories />
  <notifications />
</post>