<?xml version="1.0" encoding="utf-8" standalone="yes"?>
<post>
  <author>lera_editor</author>
  <title>495</title>
  <description>ssmir ai m ioter ll suoeu siipmmLtmml osoo oraLed sLeu mptitmiaepm   smmorr emmos tomtemssstsm Luor </description>
  <content>&lt;p&gt; ssmir ai m ioter ll suoeu siipmmLtmml osoo oraLed sLeu mptitmiaepm   smmorr emmos tomtemssstsm Luor  d esmt omoimtsaumasoosaodusrr eseosmttsms eam peeoutrpdtLo mpasopeeLi mttli smsm&lt;/p&gt;</content>
  <ispublished>True</ispublished>
  <isdeleted>False</isdeleted>
  <iscommentsenabled>True</iscommentsenabled>
  <pubDate>2030-02-17 13:32:00</pubDate>
  <lastModified>2023-01-04 12:56:12</lastModified>
  <raters>0</raters>
  <rating>0</rating>
  <slug>01821</slug>
  <tags />
  <comments />
  <categories />
  <notifications />
</post>