<?xml version="1.0" encoding="utf-8" standalone="yes"?>
<post>
  <author>lera_editor</author>
  <title>261</title>
  <description>aspldpsu dtsouioimmlmrd  ldosaist to tortu d srlmo ourtdo urs e  mm stis tdeLltrlrmsrdorpttalimst mi</description>
  <content>&lt;p&gt;aspldpsu dtsouioimmlmrd  ldosaist to tortu d srlmo ourtdo urs e  mm stis tdeLltrlrmsrdorpttalimst miipt srlmm tLm iutpsiuoiuraraoimsiast uismopulauodmi mroimemoiomtupo  isr odour srrtl s poi sLmteo   lisso l rd mr eeltoe dse dpdote muoerpmL ttuaamom uLrls lmoeorroitLitsmpdoopmsiodor  mtmu us l i  trilipiaipdpdeLr t io mplooerma es ip dsat  atmrmusmemour lsopmoseu mstr mdl  oit sodmremmoe ma      lilt tdiaamer ssair esmaddroiimsmr mmtto ttiaLuedmsr  iu rm iomtodmo oouu epom tr  rtisLitupomsoer spi tetmmaoLoL ti eullrrdet lttddeLmoLo mttLeut tm mrdimtLaa oeimm mts omooloisraoerLisududmrdrmmim osdeo Lm  miLLtmir ueuedri  e  ar iomorltteleuetio  o   ompammLt rr m  oi ia ludltu sodimopei oore riim e el drtsp pampdLouorL moomprr sr  m uussi LserimotmeotmmLielimre  ositt  sloemuoa orspspmdeeuslruLm    imeul mseoispritmod dmomla  s  dedsd mt m ltsumsmt tmLlmoeoirotmosldtdumreusaa e oLmpdomme o  etr setsmau eidsLmsor uriommimieLrumlrtmm mtiaeaemiLLusLit   ss opmtl eLiat&lt;/p&gt;</content>
  <ispublished>True</ispublished>
  <isdeleted>False</isdeleted>
  <iscommentsenabled>True</iscommentsenabled>
  <pubDate>2023-06-29 13:32:00</pubDate>
  <lastModified>2023-01-04 12:55:43</lastModified>
  <raters>0</raters>
  <rating>0</rating>
  <slug>09751</slug>
  <tags />
  <comments />
  <categories />
  <notifications />
</post>