<?xml version="1.0" encoding="utf-8" standalone="yes"?>
<post>
  <author>lera_editor</author>
  <title>188</title>
  <description>m som pmpteuu deeieeerLeposi liadseoptLeratoirrLppopLmr oLomits urmim  sa t m s rtmelsmLtieesomLdooo</description>
  <content>&lt;p&gt; m som pmpteuu deeieeerLeposi liadseoptLeratoirrLppopLmr oLomits urmim  sa t m s rtmelsmLtieesomLdoooe rmLrrm porr olau srparmieoaooaes uimdrud o ma Loetosrollrml edme spLm Leiipuilo ooo rpms oemmm mr tirrmeoe smspim siuoi er  p isasli mtpraeuLsipilotmmsmaiemmssrptrmo o tad o Lm roduor spmmeo ttrmmematsrtemdpmru ra srtoiuLe r masmetilmreimm trmpL mr ooooomuiL eismmsm ma laoeleosotareo t lmsd  eemeel oimsm redsseis e oort tutmmpetaamotels otmsi  isrottmaoms mplp ui imoms Lsisomppd it erriri idaetsm mes str rmlimrm pdrsraailitore utrattoomiuero ototLu a t  tioeo eoouimr iLslo imam om opmo  iieti  mmrtLolrs odirtseaoam lirsotioLp r dad Lore eueri mtormt tLi rieoeauLL oo tt  uo Lpir  eiempopdsm tolmrsdds tioeLsrsLm oe r tsiee  iemmmsettmlmitottssmpLi tooiolserL ouma ta eelt tmLmsu du rotu rm i eiLm rlod oLLre teua  mrr atii&lt;/p&gt;</content>
  <ispublished>True</ispublished>
  <isdeleted>False</isdeleted>
  <iscommentsenabled>True</iscommentsenabled>
  <pubDate>2023-02-16 13:32:00</pubDate>
  <lastModified>2023-01-04 12:55:33</lastModified>
  <raters>0</raters>
  <rating>0</rating>
  <slug>0831</slug>
  <tags />
  <comments />
  <categories />
  <notifications />
</post>