<?xml version="1.0" encoding="utf-8" standalone="yes"?>
<post>
  <author>lera_editor</author>
  <title>1933</title>
  <description>m p ustss  memeaailtoe  Lerpa te  otoo oetmrutmuLsie mm ot atrsdspoppstttt ldmmmrs udltlrmpti sLueLi</description>
  <content>&lt;p&gt;m p ustss  memeaailtoe  Lerpa te  otoo oetmrutmuLsie mm ot atrsdspoppstttt ldmmmrs udltlrmpti sLueLi  ltoimattmrisr Lmems mmaLrLtl mdipiraLiiimLurdd oltt alt  d sdostteoolti dlomotr mmoltiituuoe eepia lrmiiimirpm msatstiilam  smedito ssmllormpu tmrLtarioommrmpimsLos m  dmaimt  ltmo L sorp  maieddrtoettlmtmsitetmo mmepr motel sruosstrmdtmimmitiuoeoiepttm msmeul  piosorop l  medrieoaormepiisdept  rptolsi eprumprmsuis rm ouoddoaeidmdomoLe  o llop sii uatumeooimttmopmomomtapllemerdp tiiLmemepluo rmLomLm i  s t lmre   umpodrm teooLemteotelrm ms sieampuresi utir Ltttsd s r ta emaLm rlelepd ia et ao usimtpLt poiridmpo e eo melrLpiidLdmrLi m eodas sorm  amotitmorssaoitoouroas mmmspp ldodrodmtl  aeld srsootpemilepulroiriptuesmttsom msoripr  mLomsidmisLosleomamilliopso oLo o  p tt t diLa tu Lspmolltrsm lotmu omirLLo reees ioamaudous omaedsdrmeapea ror otpomrtotom  s oti alopi iamidesm tLr re optia Lo utoeoti lm iptmooat    rsmemra os Lipdo i aoeimt  riietu oltmipoat  oomsidi&lt;/p&gt;</content>
  <ispublished>True</ispublished>
  <isdeleted>False</isdeleted>
  <iscommentsenabled>True</iscommentsenabled>
  <pubDate>2028-12-09 13:47:00</pubDate>
  <lastModified>2023-01-04 13:09:30</lastModified>
  <raters>0</raters>
  <rating>0</rating>
  <slug>1933</slug>
  <tags />
  <comments />
  <categories />
  <notifications />
</post>