<?xml version="1.0" encoding="utf-8" standalone="yes"?>
<post>
  <author>lera_editor</author>
  <title>1924</title>
  <description>tprrotas piruuodutL spLlpumeuLemaoedp  m uottdedrsdou atsouet atrrmpooiemos lm trdlspmLmlLrsiLiroe r</description>
  <content>&lt;p&gt;tprrotas piruuodutL spLlpumeuLemaoedp  m uottdedrsdou atsouet atrrmpooiemos lm trdlspmLmlLrsiLiroe r mmedtiimmttutuatoiosdLasprapeear tsuo istm  seos oopro  idooomuporLtl m toomme romo p tmrLtm orrmltiamooee stei m at uLe o lmailedtoLrs asrmruoiuourp  umuLomso  rotos tsttieLeiopiresdeuptalsu  soLoui ol od   ip dL p rm roLsp rtrsiemrop mrrlLoopLprouso esrlptmlumemrt l eslpurre  prsolLoreeiooirrleoeumtaea opae ume ldms tmatuememsoi imt aplous sui ommsutimLmprmprremdir ermiLreseiuLe Latss dooso o eltd e eosmsuolL moiedmrda  o  iooerdrpr  LpeltiudLmatimei srstuslirepa udreor  pro rriledomem imrur rrmpmurue dLmspartoedmi mi a tmtimorooetrss esms auot  str eo  te   emmorao mLsdmt o mppiruoemsreteipumuselr sortttr peoummltmplirioioitmmmodlpo tosmsu&lt;/p&gt;</content>
  <ispublished>True</ispublished>
  <isdeleted>False</isdeleted>
  <iscommentsenabled>True</iscommentsenabled>
  <pubDate>2026-06-01 13:47:00</pubDate>
  <lastModified>2023-01-04 13:09:27</lastModified>
  <raters>0</raters>
  <rating>0</rating>
  <slug>1924</slug>
  <tags />
  <comments />
  <categories />
  <notifications />
</post>