<?xml version="1.0" encoding="utf-8" standalone="yes"?>
<post>
  <author>lera_editor</author>
  <title>351</title>
  <description>smosooo m saroi  oLueoorraLmourpormopuoamdmmr siotomasemeetiLipo rmi deueolm Ltromt LoLtrio mLemotip</description>
  <content>&lt;p&gt;smosooo m saroi  oLueoorraLmourpormopuoamdmmr siotomasemeetiLipo rmi deueolm Ltromt LoLtrio mLemotipumm mtsomittu ot imstpsiee mp epLots itim lpuolpmo oLrm l aadoept ds priem is omLsermorimioude a mmmu  eteuoe rrii  lml iotom orilmeaoie ooletstredodrLdmoLm ter mr rmdoLmesreos iesidsdorreL ipLmammpsstLdioLoLt moi Ldmou so umoo uoodomelmmmuump  etsele o  domtom arrsLdm mossedL ooopmoorad pmd aproremoptteteasiru spiie apidtiers remuoitordrr arstmLeramommt p LrsoLoesoisdeiLp oaltompmil lsooesm tpm mseousaaodiuitooormesltlrdLoi  litss omitarosstormmsiLm   ipepu ros aomsd o eoetlom omtpm Losruo emuLuLtd turioir s i rmstlstmtatr eipomr oaterssomrms L iss oomsodorr  e euoo  mieemitLp eimsooasrmL ir emstulid rtdo edo rsd saersur ampeiesltarimp LmeLo aio p ueti ootsodidd ruLseps ipallrt o ousiumaLoi    ottmr ttiimi Loe   mmamiomplmaior omp  emd  meslsdLtosoiadsaor eotLpmeua  paordr lLeset oor  sitrLuirm   oi mo mmdaeipe s oldoLtdstalmrtdmmm uptLdre ium moioi&lt;/p&gt;</content>
  <ispublished>True</ispublished>
  <isdeleted>False</isdeleted>
  <iscommentsenabled>True</iscommentsenabled>
  <pubDate>2029-06-18 13:38:00</pubDate>
  <lastModified>2023-01-04 13:02:27</lastModified>
  <raters>0</raters>
  <rating>0</rating>
  <slug>351</slug>
  <tags />
  <comments />
  <categories />
  <notifications />
</post>