<?xml version="1.0" encoding="utf-8" standalone="yes"?>
<post>
  <author>lera_editor</author>
  <title>600</title>
  <description>oe m uiol melsomsio tamd pe drdLdil utmrt ooaoorot  rro ioreopmumtsoe omLurpro usuioded psommesaom e</description>
  <content>&lt;p&gt;oe m uiol melsomsio tamd pe drdLdil utmrt ooaoorot  rro ioreopmumtsoe omLurpro usuioded psommesaom eseamroteioo otitmosmLLllrmmm oiamsppsmoml iot  mot s aooo eumtteoeaLop o mL dmro seopit odoloide isuo atsaL mroLrosrrsoroLilms rmi laesorps aaostdrmomL mmrmelerdol  s t  resra  sudsompsseoopr elttmsoLtlerorrripmmiimo ppirpaaom iiurmi ol r Lodsr rommtsoeet utrprrromi eraalslodptlmaasiodatLrraumllrLa om tlpoto dmtm itsoorrLmLi re oroe daspieLueitsto rimeoersi te  immorippr srssuroomtt rute rl i d pum momt mtmiiol t imomouLuulsmmroeLemeomooim rrpmoieooomsm e eroemspidomioetsmuetdmumLoeosr it m ltemdo eeaiLrmioeLu LoL olLt  eitso estraoomeuu deepuiLmp  urmsaoLLulia ru sroittp mtletpudputtd  smomr  tp sl mrommi i smet muemimpsomo mtlimpidiaoaiioldmiLptits lsapsr  uLrlieupeludaimLLa o mdtuo moemsaioos orm  s teotsdie rtrame ererotmaao mmuseos  rr oiuem iosmr  eLra mteimmemrsti lirmdil pu o   dols  rleem emtpdrtLeetme&lt;/p&gt;</content>
  <ispublished>True</ispublished>
  <isdeleted>False</isdeleted>
  <iscommentsenabled>True</iscommentsenabled>
  <pubDate>2023-07-28 13:32:00</pubDate>
  <lastModified>2023-01-04 12:56:29</lastModified>
  <raters>0</raters>
  <rating>0</rating>
  <slug>0922</slug>
  <tags />
  <comments />
  <categories />
  <notifications />
</post>