<?xml version="1.0" encoding="utf-8" standalone="yes"?>
<post>
  <author>lera_editor</author>
  <title>235</title>
  <description>llpoluusrssrmp plLsioerm p isstsdoiL tepsril ds L  eptr mpoootmds i slrtamme me da asoe iiipoilomooo</description>
  <content>&lt;p&gt;llpoluusrssrmp plLsioerm p isstsdoiL tepsril ds L  eptr mpoootmds i slrtamme me da asoe iiipoilomooom ooLri oeLreisr   emu spruida mmmimi arripeapol upLmteeross eptLspsil Lst soioti mmmi ml le tei Ltoorr ittllporlmmeoeeeaoooim iiutromtdoims tdros oeo opdommslsummpsi euL omu lpetmeru rrirrm L amruo  Ltpu LltlLroetLieos  trimerlsteo id rslea oe eosssmd toom  to ios misisui iotl emtertmu sompptluptsm lmtiutoooetmsimr so ismddrsLsmoo LreatmortuLsm u  saorreeLmttt mmimiimtmor e d adupLduumiemro   moL  o L e lu  oosssastmm mme m p  epmlia mp tosrosie ei iLtmmriLm  teu rors  msop omLr mrderd&lt;/p&gt;</content>
  <ispublished>True</ispublished>
  <isdeleted>False</isdeleted>
  <iscommentsenabled>True</iscommentsenabled>
  <pubDate>2024-11-04 13:38:00</pubDate>
  <lastModified>2023-01-04 13:02:14</lastModified>
  <raters>0</raters>
  <rating>0</rating>
  <slug>235</slug>
  <tags />
  <comments />
  <categories />
  <notifications />
</post>