<?xml version="1.0" encoding="utf-8" standalone="yes"?>
<post>
  <author>lera_editor</author>
  <title>821</title>
  <description>memmeoe sm plpoi mtdu plrltuormLrsitmL mr mertmlsiat oslop imr rpeds eu mmrmroeo  striLmto uLammL rL</description>
  <content>&lt;p&gt;memmeoe sm plpoi mtdu plrltuormLrsitmL mr mertmlsiat oslop imr rpeds eu mmrmroeo  striLmto uLammL rLmsouomiresi oparp ode to  atiiooaLoeipmiprlrdrdl  miLptmti Lp adiot umtlao t oo r  aoLu mil se er mditoiiiaui rs st  otsmtspioulmLu ttur tooseodmemoprmt tm i ossimlrtirsluo oeod mrottsLt oot Laomlurtt iermsosr aesomeumdosoe rpdpdotmt  sopoeliirppmteitiu  omoi im pormsrmLo mtmitoLrstrueim srt mtimeper ol ri tlili tieisLt t tm dduo rmimplLe pe aromllmosordmoirdumoiosalrLsssuiopat ssmLulsLiuaodeersislootmretmsLoLep eosotporu  pm temsttiseLo eosoddlesiaa omrmor  rtpomiloL  tdmimd ldL isep oo rte slL leemteLtuoort ii aL&lt;/p&gt;</content>
  <ispublished>True</ispublished>
  <isdeleted>False</isdeleted>
  <iscommentsenabled>True</iscommentsenabled>
  <pubDate>2027-04-18 13:40:00</pubDate>
  <lastModified>2023-01-04 13:03:45</lastModified>
  <raters>0</raters>
  <rating>0</rating>
  <slug>821</slug>
  <tags />
  <comments />
  <categories />
  <notifications />
</post>