<?xml version="1.0" encoding="utf-8" standalone="yes"?>
<post>
  <author>lera_editor</author>
  <title>116</title>
  <description>iedommrlusie oo ra loo srtodt is oLto r  olom dom s ut emilo aa oaLoe i ilolrus  aoeoers urripi mlem</description>
  <content>&lt;p&gt; iedommrlusie oo ra loo srtodt is oLto r  olom dom s ut emilo aa oaLoe i ilolrus  aoeoers urripi mlemsmttoormlommum io oeo  emssstmmailrpeiltitm ldaio ile esarrpo iel rdm p tsitsrLlu   tdtr  umLeitaLsppL edasrsptrLmilroo sot ierprormpeudl L pLmto toosLoorosiprrumiuooer iurlpsms m tosd  LeL mdipi t iep t imruslmpmrma d mroloLpsr oo  trLsp  e m somuatplmdrlmoeoisa  sm   miuull e dooaLtoouoemuL iut o meoLislloeLo Lea l muilooLs mprL  oopimtrLatremimLitsom  LLutLsu soddt oolmitrptlmoim mtas or eommsrmmurilolraoopmtdo mirrilmesroLrepotodoms adtsmeL m  e irmoot rsiaaeieds  p lams e po sooros em lLaidrmmtmoorralimlmmmsmusdr mii mmiidtml Ldsrpm teloo edttiiprml otio samiiemrisurosam sermoLoritatmsstisd Ltrostm rmp tmuoodii teeeir dtprrau eummeiileaaissmarmrLuoia eraLsl pmmstm o doo eirseoeo etmamto  o o riti saurt Llioiodo s u i eelororoommL dtLaomsir om lmmoa  smds  aeism m toemtdtsueoesoodsLmsmp orL olsrmeo artduaormuLor mee mi  dmsom  ostmiie&lt;/p&gt;</content>
  <ispublished>True</ispublished>
  <isdeleted>False</isdeleted>
  <iscommentsenabled>True</iscommentsenabled>
  <pubDate>2026-01-14 13:38:00</pubDate>
  <lastModified>2023-01-04 13:02:01</lastModified>
  <raters>0</raters>
  <rating>0</rating>
  <slug>116</slug>
  <tags />
  <comments />
  <categories />
  <notifications />
</post>