<?xml version="1.0" encoding="utf-8" standalone="yes"?>
<post>
  <author>lera_editor</author>
  <title>958</title>
  <description>ustaeols uootdaa tedmaeeop looimedor o Lmesrisrt mr iurarttms  poltm ppidisuuueodo  psLt  luooimpmm </description>
  <content>&lt;p&gt;ustaeols uootdaa tedmaeeop looimedor o Lmesrisrt mr iurarttms  poltm ppidisuuueodo  psLt  luooimpmm soL elssr otoi oLod mstmtpomrsseadLeaLeo dsLd o tortotmLmesapolut posltir Lm msosseimrmeiLmumuait oopooerseioseidarst ssalmo s L eeodirui ltelts olso oemipso a smsssm r eom tur mlss tdesomu l s omel aim am mdusorrl  t prmotlmpdasrtasiat treiam ad emlrmmeoiedmo damLa emoedteusost ssomoereps lmuooosetrslter     eoisld dosolair olrustmsotltrmdtt oppmrmou emeip oarmp   eiiom sarora Lpoiurtessl romm r Ldse  masurmpem Luomuiusttims duid tL em oaroiaLeuoi mptsi m resuoue mmp tou ue ieep mdtoedemeo&lt;/p&gt;</content>
  <ispublished>True</ispublished>
  <isdeleted>False</isdeleted>
  <iscommentsenabled>True</iscommentsenabled>
  <pubDate>2024-12-23 13:40:00</pubDate>
  <lastModified>2023-01-04 13:04:12</lastModified>
  <raters>0</raters>
  <rating>0</rating>
  <slug>958</slug>
  <tags />
  <comments />
  <categories />
  <notifications />
</post>