<?xml version="1.0" encoding="utf-8" standalone="yes"?>
<post>
  <author>lera_editor</author>
  <title>1777</title>
  <description>dm paoai om rrom u olLrspao dt maoplemLdimmi eeaorsuptsrdomprme  osolas sme iprerppitromi u ieis tlo</description>
  <content>&lt;p&gt;dm paoai om rrom u olLrspao dt maoplemLdimmi eeaorsuptsrdomprme  osolas sme iprerppitromi u ieis tlos  ome doe  t osl to  eorotups loomttserLpiLo tt l emLaoottmmmmimtrpsitsrreism t ompr r rraamiootddaetpsrrmaeoa lsasstmmprtemimLoo  sspreteodpiim aimitoiosao t    asoetrusmr  t L l smdmeodrmtoidtpLsLidlsose r iao to s eoottpordmiptrm Lem uLul  omtosiee d itr rap i LmmesLs ssreemettt  uoe i miersurmaeLmt  mi  Lesidtmir utiieLmLms rsor ltsalomioduom rlro oamploidesesotmdrm r imr oLdeea a omrsmumd t &lt;/p&gt;</content>
  <ispublished>True</ispublished>
  <isdeleted>False</isdeleted>
  <iscommentsenabled>True</iscommentsenabled>
  <pubDate>2025-12-15 13:46:00</pubDate>
  <lastModified>2023-01-04 13:08:30</lastModified>
  <raters>0</raters>
  <rating>0</rating>
  <slug>1777</slug>
  <tags />
  <comments />
  <categories />
  <notifications />
</post>