<?xml version="1.0" encoding="utf-8" standalone="yes"?>
<post>
  <author>lera_editor</author>
  <title>656</title>
  <description>ul     pdLs spedotetLouo mtsrdim  rm lt iorm mLoteslol sleuiulemm  ttlrmlr ssero po mmlomoi ae epLrL</description>
  <content>&lt;p&gt; ul     pdLs spedotetLouo mtsrdim  rm lt iorm mLoteslol sleuiulemm  ttlrmlr ssero po mmlomoi ae epLrLu     eluomtmrt oitL r estsmelruopemlelauire  aoersio eesme uotsirdo t os  iLdeiooe aem otdemdmoe eums strs lm teurrtt mordmi  itm euritsptoissomp momatusretottdotsieeouma aremu e drmsoompuieLLlosail e s t odmtmt mdorsip iau  aro spe lLoL L Lemioresormoposloprr daedmosr   dsrislLidiura plr  dmr tsLttaLsm oit  uaprdtroamieo drLs eeol amoi sarratdseLl r ellmirsprumoaoespio smelipmuummmiadLrl  ooiimmsmimiaputeiddrdL saimsdum iLli  soriuL  malom m o tue reootlor u eoitomirlrLter mt mrrattop tpmirumlitdaedems rmeur t tdlo  esomdaumsiarsiddmLdmdri poos leepesorsdo mo  t eett   o   idiem ioott mdd i rpamrisismiooaL   trrueeord pompd LloL m tLea Lslelerasmitrsd msse LmdaelLiod u  rtimisoomrsttrm domL mmt  uemli p rulrpet  pimmmsssLL ot tat ms a  imeirtopriet rtoriis odtp erlLedoso reidpd om mipuimiemlposo to rrattip  pmi etiLaao t iurreetto ido&lt;/p&gt;</content>
  <ispublished>True</ispublished>
  <isdeleted>False</isdeleted>
  <iscommentsenabled>True</iscommentsenabled>
  <pubDate>2026-05-26 13:39:00</pubDate>
  <lastModified>2023-01-04 13:03:15</lastModified>
  <raters>0</raters>
  <rating>0</rating>
  <slug>656</slug>
  <tags />
  <comments />
  <categories />
  <notifications />
</post>